Workbook

Sheet Read me
A1: Khas Tracker risk register (review copy)
A2: As of 2026-10-31. Method: 01-risk/methodology.md (NIST SP 800-30 Rev 1, ISO 27001 6.1.2 / 6.1.3).
A4: How to review
A5: 1. Go to the Risks sheet. Each row is one risk. Use the filter arrows to sort by Current level.
A6: 2. Blue numbers are inputs: likelihood (L) and impact (I), 1 = Very Low ... 5 = Very High. Change one and the score and level recalculate.
A7: 3. Fill in the two yellow columns at the far right: "Your decision" (Agree / Change) and "Your notes" (what to change and why).
A8: 4. Rows already marked "Decided by M. Khas" were decided in chat; you can still change them.
A10: Columns
A11: Score = L x I (1-25), only for sorting. Level = SP 800-30 Table I-2 lookup (see Scales sheet). The level drives decisions.
A12: Inherent = without Khas Tracker's own controls. Current = with verified controls today. Target = after the planned action.
A13: Example row: R-01. Inherent L 4, I 5 -> score 20, Very High. Current L 2, I 5 -> 10, Moderate. Target L 1, I 5 -> 5, Low.
A15: Source of truth: 01-risk/risk-register.csv. This workbook is generated from the same data for easier review.

Sheet Risks
A1: Risk ID | B1: Risk | C1: Threat event | D1: Threat sources | E1: MITRE ATT&CK | F1: Assets | G1: Vulnerabilities / conditions | H1: Existing controls (verified) | I1: Scoring rationale | J1: Inherent L | K1: Inherent I | L1: Inherent score | M1: Inherent level | N1: Current L | O1: Current I | P1: Current score | Q1: Current level | R1: Treatment | S1: Planned action | T1: Target L | U1: Target I | V1: Target score | W1: Target level | X1: Owner | Y1: Status | Z1: Next review | AA1: Your decision | AB1: Your notes
A2: R-01 | B2: Administrator identity or credential store compromised | C2: An attacker gains the administrator's AWS credentials and second factor through phishing, a compromised identity account or a stolen unlocked device, and takes control of the AWS account, including the ability to delete data and backups | D2: TS-01; TS-02 | E2: T1566; T1555; T1078.004; T1485; T1496 | F2: A-08; A-09; A-01; A-02 | G2: V-01; V-06; V-07; V-08; V-14 | H2: MFA on AWS root and admin user; MFA on administrator identity accounts; no AWS access keys on the operator's computer (CloudShell only); budget alerts | I2: Likelihood Low: MFA blocks password-only attacks, but the factors are not independent, so one compromise can yield both. Impact Very High: full control of production and backups | J2: 4 | K2: 5 | L2: =J2*K2 -> 20 | M2: =INDEX(Scales!$C$12:$G$16,6-J2,K2) -> Very High | N2: 2 | O2: 5 | P2: =N2*O2 -> 10 | Q2: =INDEX(Scales!$C$12:$G$16,6-N2,O2) -> Moderate | R2: Mitigate | S2: Move AWS root and admin MFA to phishing-resistant factors (security keys or passkeys) kept outside the password store; lock backups against deletion (AWS Backup Vault Lock); test admin recovery (with R-19) | T2: 1 | U2: 5 | V2: =T2*U2 -> 5 | W2: =INDEX(Scales!$C$12:$G$16,6-T2,U2) -> Low | X2: M. Khas | Y2: Decided by M. Khas, 2026-10-31 | Z2: 2027-04-30 | AA2: Agree
A3: R-02 | B3: Malicious deploy through a compromised identity or code-host account | C3: An attacker takes over the identity account that signs in to the code host, pushes a change to main, and the pipeline deploys an app that captures users' passphrases | D3: TS-01; TS-02 | E3: T1078; T1195.002; T1056.003 | F3: A-06; A-05; A-09; A-01 | G3: V-02; V-03; V-06 | H3: MFA on the code host and identity account; deploy role usable only from the main branch of one repository; 1-hour deploy sessions; full Git history of every change | I3: Likelihood Low: MFA on both accounts, but no approval step stands between a push and production. Impact Very High: every user's data readable from then on (breaks SC-1) | J3: 4 | K3: 5 | L3: =J3*K3 -> 20 | M3: =INDEX(Scales!$C$12:$G$16,6-J3,K3) -> Very High | N3: 2 | O3: 5 | P3: =N3*O3 -> 10 | Q3: =INDEX(Scales!$C$12:$G$16,6-N3,O3) -> Moderate | R3: Mitigate | S3: Phishing-resistant MFA (passkey or security key) on the identity account and code host; give the code host its own sign-in; email notification on every production deploy; review the code host security log monthly | T3: 1 | U3: 5 | V3: =T3*U3 -> 5 | W3: =INDEX(Scales!$C$12:$G$16,6-T3,U3) -> Low | X3: M. Khas | Y3: Decided by M. Khas, 2026-10-31 | Z3: 2027-04-30 | AA3: Agree
A4: R-03 | B4: Unreviewed change breaks the app or corrupts data | C4: The operator pushes a faulty change (for example a sync or encryption bug) that deploys straight to production and breaks the app or damages stored records | D4: TS-06; TS-07 | F4: A-05; A-01; A-11 | G4: V-03; PC-01 | H4: CI runs unit tests and a type check before every deploy; deploys only from main; rollback by revert; DynamoDB deletion protection and point-in-time recovery; encrypted copies on users' devices | I4: Likelihood Moderate: frequent solo changes with no second review. Impact Moderate: point-in-time recovery and device copies limit lasting loss | J4: 4 | K4: 5 | L4: =J4*K4 -> 20 | M4: =INDEX(Scales!$C$12:$G$16,6-J4,K4) -> Very High | N4: 3 | O4: 3 | P4: =N4*O4 -> 9 | Q4: =INDEX(Scales!$C$12:$G$16,6-N4,O4) -> Moderate | R4: Mitigate | S4: Work on branches with a pull request and a self-review checklist; CI runs on pull requests before merge; each merged PR is the change approval record | T4: 2 | U4: 3 | V4: =T4*U4 -> 6 | W4: =INDEX(Scales!$C$12:$G$16,6-T4,U4) -> Low | X4: M. Khas | Y4: Decided by M. Khas, 2026-10-31 | Z4: 2027-04-30 | AA4: Agree
A5: R-04 | B5: Operator ships a passphrase-capturing build | C5: The operator, deliberately or under pressure, deploys app code that captures users' passphrases | D5: TS-05 | E5: T1056.003 | F5: A-05; A-01 | G5: PC-01; PC-02 | H5: Git history makes any code change visible after the fact; users know the operator personally | I5: Likelihood Very Low: no motive and personal relationships with every user. Impact Very High: all content readable | J5: 1 | K5: 5 | L5: =J5*K5 -> 5 | M5: =INDEX(Scales!$C$12:$G$16,6-J5,K5) -> Low | N5: 1 | O5: 5 | P5: =N5*O5 -> 5 | Q5: =INDEX(Scales!$C$12:$G$16,6-N5,O5) -> Low | R5: Accept | S5: Accepted at design time: the risk cannot reach zero while the operator serves the code, even with a second person. Add a free detective control: a changelog of every production deploy that users can see. Re-assess if a second admin is added (T-06) or users who are not friends or family join (T-04) | T5: 1 | U5: 5 | V5: =T5*U5 -> 5 | W5: =INDEX(Scales!$C$12:$G$16,6-T5,U5) -> Low | X5: M. Khas | Y5: Decided by M. Khas, 2026-10-31 | Z5: 2027-10-31 | AA5: Agree | AB5: I think agree? The only way this could be mitigated is if I had a second person right? If there is any other way to absolutely mitigate this, I would love to implement.
A6: R-05 | B6: Malicious dependency or Action runs in the deploy job | C6: A compromised npm package or GitHub Action runs inside the deploy job, uses the deploy credentials, and changes the app or the AWS account | D6: TS-03 | E6: T1195.001; T1078.004 | F6: A-06; A-07; A-08; A-05 | G6: V-04; V-05 | H6: Small direct dependency set (2 runtime, 5 development packages); no long-lived AWS keys in CI (OIDC); 1-hour sessions; deploy role limited to main; CI tests | I6: Likelihood Low: supply-chain attacks are common but untargeted, and the direct dependency set is small; the transitive tree is much larger. Impact Very High: the deploy role is administrator-equivalent | J6: 3 | K6: 5 | L6: =J6*K6 -> 15 | M6: =INDEX(Scales!$C$12:$G$16,6-J6,K6) -> High | N6: 2 | O6: 5 | P6: =N6*O6 -> 10 | Q6: =INDEX(Scales!$C$12:$G$16,6-N6,O6) -> Moderate | R6: Mitigate | S6: Commit a lockfile and install with npm ci; give the deploy credentials only to the deploy step; pin GitHub Actions to commit SHAs; turn on Dependabot alerts; later, narrow the CDK deploy permissions | T6: 1 | U6: 5 | V6: =T6*U6 -> 5 | W6: =INDEX(Scales!$C$12:$G$16,6-T6,U6) -> Low | X6: M. Khas | Y6: Decided by M. Khas, 2026-10-31 | Z6: 2027-04-30 | AA6: Agree
A7: R-06 | B7: Incident goes undetected or cannot be investigated | C7: An attack or misuse in the AWS account or app is not noticed, or cannot be reconstructed afterwards because the needed logs do not exist | D7: TS-01; TS-02; TS-03; TS-05 | E7: T1562.008 | F7: A-12; A-08 | G7: V-06 | H7: Budget alerts; AWS CloudTrail event history (AWS default, 90 days, management events); Lambda error logs (14 days) | I7: Likelihood Moderate: no security alerting at all today. Impact High: affected users could not be told what was exposed | J7: 4 | K7: 4 | L7: =J7*K7 -> 16 | M7: =INDEX(Scales!$C$12:$G$16,6-J7,K7) -> High | N7: 3 | O7: 4 | P7: =N7*O7 -> 12 | Q7: =INDEX(Scales!$C$12:$G$16,6-N7,O7) -> Moderate | R7: Mitigate | S7: Free controls only (no GuardDuty, a cost decision): verify or create a CloudTrail trail with log file validation; free email alerts on root and admin sign-in and on logging changes; keep app logs longer. Remaining Moderate risk to be accepted with a written reason after treatment | T7: 3 | U7: 4 | V7: =T7*U7 -> 12 | W7: =INDEX(Scales!$C$12:$G$16,6-T7,U7) -> Moderate | X7: M. Khas | Y7: Decided by M. Khas, 2026-10-31 | Z7: 2027-04-30 | AA7: Agree
A8: R-07 | B8: User account taken over | C8: An attacker or someone close to a user gets their password and authenticator code (phishing, reuse, access to their phone) and signs in as them | D8: TS-01; TS-04 | E8: T1566.002; T1078; T1111; T1485 | F8: A-04; A-01 | G8: V-12; V-13 | H8: Invite-only accounts; TOTP MFA required; 10-character minimum password; generic sign-in errors; 1-hour tokens; API throttling; end-to-end encryption means a taken-over account exposes only ciphertext | I8: Likelihood Low: MFA required and a small, invite-only user base. Impact Moderate: the attacker gets ciphertext only but could delete that user's records (recoverable) | J8: 4 | K8: 4 | L8: =J8*K8 -> 16 | M8: =INDEX(Scales!$C$12:$G$16,6-J8,K8) -> High | N8: 2 | O8: 3 | P8: =N8*O8 -> 6 | Q8: =INDEX(Scales!$C$12:$G$16,6-N8,O8) -> Low | R8: Mitigate | S8: Move the user pool to the Cognito Essentials plan (free under 10,000 monthly users) and offer passkey sign-in, which resists phishing; tell users how to protect their account in the Phase 6 privacy notice | T8: 1 | U8: 3 | V8: =T8*U8 -> 3 | W8: =INDEX(Scales!$C$12:$G$16,6-T8,U8) -> Very Low | X8: M. Khas | Y8: Decided by M. Khas, 2026-10-31 | Z8: 2027-10-31 | AA8: Agree | AB8: Is this where we could mitigate by having anoption to download an offline copy of their data? How coud we mitigate this if we wanted to.
A9: R-08 | B9: Passphrase cracked offline | C9: Someone who already holds a user's keyring (for example after an AWS breach) guesses a weak passphrase offline and decrypts that user's data | D9: TS-01; TS-02; TS-05 | E9: T1110.002 | F9: A-01; A-02 | G9: V-15 | H9: PBKDF2-SHA256 with 600,000 iterations; passphrase at least 12 characters; 24-character random recovery code; keyring reachable only after another compromise (R-01, R-02, R-05) | I9: Likelihood Very Low: needs a prior AWS compromise plus a weak passphrase. Impact High: one user's content | J9: 3 | K9: 5 | L9: =J9*K9 -> 15 | M9: =INDEX(Scales!$C$12:$G$16,6-J9,K9) -> High | N9: 1 | O9: 4 | P9: =N9*O9 -> 4 | Q9: =INDEX(Scales!$C$12:$G$16,6-N9,O9) -> Low | R9: Mitigate | S9: Add a self-hosted passphrase strength check (block common passphrases, encourage several words), with no third-party scripts | T9: 1 | U9: 4 | V9: =T9*U9 -> 4 | W9: =INDEX(Scales!$C$12:$G$16,6-T9,U9) -> Low | X9: M. Khas | Y9: Decided by M. Khas, 2026-10-31 | Z9: 2027-10-31 | AA9: Agree | AB9: yeah, if a passphrase strength meter is the best we can do, we should do that.
A10: R-09 | B10: Record metadata shows when users log | C10: The operator, AWS or anyone who reaches the table sees record names and timestamps that show which days each user logged something | D10: TS-05; TS-01 | E10: T1530 | F10: A-03 | G10: V-09; PC-03 | H10: Only record names, timestamps and sizes are visible, never content; table access limited to the operator | I10: Likelihood Moderate: the operator sees metadata whenever doing support. Impact Moderate: activity dates of several users | J10: 3 | K10: 3 | L10: =J10*K10 -> 9 | M10: =INDEX(Scales!$C$12:$G$16,6-J10,K10) -> Moderate | N10: 3 | O10: 3 | P10: =N10*O10 -> 9 | Q10: =INDEX(Scales!$C$12:$G$16,6-N10,O10) -> Moderate | R10: Mitigate | S10: Change how records are named so stored keys no longer reveal dates (for example, keys derived with the user's data key); only sync timestamps would remain. Engineering change in the app | T10: 3 | U10: 2 | V10: =T10*U10 -> 6 | W10: =INDEX(Scales!$C$12:$G$16,6-T10,U10) -> Low | X10: M. Khas | Y10: Decided by M. Khas, 2026-10-31 | Z10: 2027-04-30 | AA10: Agree
A11: R-10 | B11: Deleted users remain in backups for years | C11: A user leaves and asks for deletion, but encrypted copies of their data stay in backups for up to 3 years | D11: TS-10 | F11: A-02; A-14 | G11: V-10; V-11 | H11: Backups hold ciphertext only, unreadable without the user's passphrase | I11: Likelihood Moderate: someone among 10 users may leave in a given year. Impact Low: data is unreadable; harm is to trust and promises | J11: 3 | K11: 2 | L11: =J11*K11 -> 6 | M11: =INDEX(Scales!$C$12:$G$16,6-J11,K11) -> Low | N11: 3 | O11: 2 | P11: =N11*O11 -> 6 | Q11: =INDEX(Scales!$C$12:$G$16,6-N11,O11) -> Low | R11: Mitigate | S11: Retention schedule and plain disclosure in the privacy notice (Phase 6); decide whether 3-year copy retention is needed | T11: 2 | U11: 2 | V11: =T11*U11 -> 4 | W11: =INDEX(Scales!$C$12:$G$16,6-T11,U11) -> Low | X11: M. Khas | Y11: Decided by M. Khas, 2026-10-31 | Z11: 2027-10-31 | AA11: Agree | AB11: Mitigate
A12: R-11 | B12: Privacy obligations not met | C12: A user or a person they record complains, or a law applies, and there is no notice, terms or record of how requests were handled | D12: TS-10 | F12: A-14 | G12: V-11; PC-03; PC-04 | H12: Users are known personally; content is end-to-end encrypted; commitments made in the invitation email and setup screens | I12: Likelihood Low: friends and family are unlikely to complain formally. Impact High: formal complaint or consumer health law exposure (trigger T-03) | J12: 2 | K12: 4 | L12: =J12*K12 -> 8 | M12: =INDEX(Scales!$C$12:$G$16,6-J12,K12) -> Low | N12: 2 | O12: 4 | P12: =N12*O12 -> 8 | Q12: =INDEX(Scales!$C$12:$G$16,6-N12,O12) -> Low | R12: Mitigate | S12: Privacy notice and terms, a request log, and the applicable-law analysis including non-user data (Phase 6) | T12: 1 | U12: 4 | V12: =T12*U12 -> 4 | W12: =INDEX(Scales!$C$12:$G$16,6-T12,U12) -> Low | X12: M. Khas | Y12: Decided by M. Khas, 2026-10-31 | Z12: 2027-10-31 | AA12: Agree | AB12: Mitigate
A13: R-12 | B13: User data permanently lost | C13: A bug, an admin mistake (such as deleting the wrong account) or an AWS fault destroys records, and the restore fails or was never practised | D13: TS-06; TS-07; TS-08 | F13: A-01; A-02 | G13: V-07 | H13: Point-in-time recovery (35 days); daily backups (35 days) with a cross-region copy (3 years); table deletion protection; encrypted copies on users' devices | I13: Likelihood Low: several independent copies exist, but restore has never been recorded as tested. Impact High: a user's history lost for good | J13: 3 | K13: 5 | L13: =J13*K13 -> 15 | M13: =INDEX(Scales!$C$12:$G$16,6-J13,K13) -> High | N13: 2 | O13: 4 | P13: =N13*O13 -> 8 | Q13: =INDEX(Scales!$C$12:$G$16,6-N13,O13) -> Low | R13: Mitigate | S13: Run and record a restore test at least yearly; bring the copy vault into infrastructure code or document it; backup lock (with R-01) | T13: 1 | U13: 4 | V13: =T13*U13 -> 4 | W13: =INDEX(Scales!$C$12:$G$16,6-T13,U13) -> Low | X13: M. Khas | Y13: Decided by M. Khas, 2026-10-31 | Z13: 2027-10-31 | AA13: Agree | AB13: Mitigate
A14: R-13 | B14: Operator unavailable for an extended period | C14: The operator cannot run the service for weeks (illness, life events); nobody else can fix problems, help users or keep the account paid | D14: TS-09 | F14: A-13 | G14: PC-01 | H14: Serverless service runs without intervention; domain auto-renews; backups are automatic; users keep encrypted copies on their devices | I14: Likelihood Low. Impact High: an outage of more than a week is possible and users have no way to export their data | J14: 2 | K14: 4 | L14: =J14*K14 -> 8 | M14: =INDEX(Scales!$C$12:$G$16,6-J14,K14) -> Low | N14: 2 | O14: 4 | P14: =N14*O14 -> 8 | Q14: =INDEX(Scales!$C$12:$G$16,6-N14,O14) -> Low | R14: Mitigate | S14: A short continuity note for a trusted person (what to tell users, how to shut down cleanly); turn the user backup download back on | T14: 2 | U14: 3 | V14: =T14*U14 -> 6 | W14: =INDEX(Scales!$C$12:$G$16,6-T14,U14) -> Low | X14: M. Khas | Y14: Decided by M. Khas, 2026-10-31 | Z14: 2027-10-31 | AA14: Agree | AB14: Mitigate
A15: R-14 | B15: Outage or cost spike | C15: An AWS fault, a traffic flood or abuse of the API makes sync unavailable or runs up the bill | D15: TS-01; TS-07; TS-08 | E15: T1499 | F15: A-11; A-05 | G15: PC-06 | H15: App works offline and syncs later; API throttling (10 requests/second, burst 20); CloudFront in front of all traffic; AWS Shield Standard (provided by AWS); budget alerts | I15: Likelihood Moderate: regional AWS issues happen. Impact Low: the app keeps working offline | J15: 3 | K15: 3 | L15: =J15*K15 -> 9 | M15: =INDEX(Scales!$C$12:$G$16,6-J15,K15) -> Moderate | N15: 3 | O15: 2 | P15: =N15*O15 -> 6 | Q15: =INDEX(Scales!$C$12:$G$16,6-N15,O15) -> Low | R15: Accept | S15: Accept; within the moderate appetite for outages | T15: 3 | U15: 2 | V15: =T15*U15 -> 6 | W15: =INDEX(Scales!$C$12:$G$16,6-T15,U15) -> Low | X15: M. Khas | Y15: Decided by M. Khas, 2026-10-31 | Z15: 2027-10-31 | AA15: Agree | AB15: Accept
A16: R-15 | B16: Domain or DNS hijacked, or domain lapses | C16: The domain is transferred, its DNS changed or it expires, and users are sent to a fake app that captures passphrases | D16: TS-01; TS-02; TS-06 | E16: T1584.001; T1056.003 | F16: A-10 | G16: V-14 | H16: Registration and DNS protected by AWS account controls (R-01); auto-renew on; HSTS for one year; TLS certificate validated by DNS | I16: Likelihood Very Low: needs an AWS compromise or a registrar failure. Impact Very High: a fake app could capture passphrases | J16: 2 | K16: 5 | L16: =J16*K16 -> 10 | M16: =INDEX(Scales!$C$12:$G$16,6-J16,K16) -> Moderate | N16: 1 | O16: 5 | P16: =N16*O16 -> 5 | Q16: =INDEX(Scales!$C$12:$G$16,6-N16,O16) -> Low | R16: Mitigate | S16: Free checks under the confidentiality rule (methodology 4.2): verify registrar transfer lock, auto-renew, contacts and renewal payment, and add them to the Phase 4 automated checks. Residual risk cannot reach zero; the aim is verified controls with evidence | T16: 1 | U16: 5 | V16: =T16*U16 -> 5 | W16: =INDEX(Scales!$C$12:$G$16,6-T16,U16) -> Low | X16: M. Khas | Y16: Decided by M. Khas, 2026-10-31 | Z16: 2027-10-31 | AA16: Agree | AB16: Mitigate, and we need to validate that this CANNOT happen.
A17: R-16 | B17: User mailbox exposes invitation password or recovery code | C17: Someone with access to a user's mailbox uses the temporary password or a self-emailed recovery code | D17: TS-01; TS-04 | E17: T1114 | F17: A-04; A-01 | G17: V-13 | H17: Temporary password expires in 7 days and must be changed; TOTP still required to sign in; a recovery code alone cannot sign in | I17: Likelihood Low. Impact Low: the attacker still needs the user's authenticator to reach any data | J17: 3 | K17: 4 | L17: =J17*K17 -> 12 | M17: =INDEX(Scales!$C$12:$G$16,6-J17,K17) -> Moderate | N17: 2 | O17: 2 | P17: =N17*O17 -> 4 | Q17: =INDEX(Scales!$C$12:$G$16,6-N17,O17) -> Low | R17: Accept | S17: User guidance on storing the recovery code in the Phase 6 privacy notice | T17: 2 | U17: 2 | V17: =T17*U17 -> 4 | W17: =INDEX(Scales!$C$12:$G$16,6-T17,U17) -> Low | X17: M. Khas | Y17: Decided by M. Khas, 2026-10-31 | Z17: 2027-10-31 | AA17: Agree | AB17: Accept
A18: R-17 | B18: Client-side code flaw exposes plaintext | C18: A flaw such as cross-site scripting lets an attacker run script in the app and read decrypted data in the browser | D18: TS-01 | E18: T1189; T1059.007 | F18: A-05; A-01 | H18: Strict Content Security Policy (scripts only from the app's own origin, no inline scripts); no third-party scripts or frameworks; framing blocked; no referrer sent | I18: Likelihood Very Low: strict CSP and no third-party code. Impact Very High: plaintext readable in the browser | J18: 3 | K18: 5 | L18: =J18*K18 -> 15 | M18: =INDEX(Scales!$C$12:$G$16,6-J18,K18) -> High | N18: 1 | O18: 5 | P18: =N18*O18 -> 5 | Q18: =INDEX(Scales!$C$12:$G$16,6-N18,O18) -> Low | R18: Mitigate | S18: Add Trusted Types to the Content Security Policy (require-trusted-types-for 'script'), free under the confidentiality rule; keep the CSP strict and re-assess if any third-party script or framework is added | T18: 1 | U18: 5 | V18: =T18*U18 -> 5 | W18: =INDEX(Scales!$C$12:$G$16,6-T18,U18) -> Low | X18: M. Khas | Y18: Decided by M. Khas, 2026-10-31 | Z18: 2027-10-31 | AA18: Agree | AB18: I don’t want to accept this if I don’t want to, or are we saying that this isn't actually an issue?
A19: R-18 | B19: API authorization flaw between users | C19: A flaw in the sync API lets one user read, change or delete another user's records | D19: TS-04; TS-01 | E19: T1190 | F19: A-11; A-01 | H19: JWT required on every API route; Lambda takes the user ID only from the verified token; user ID and record key bound into each ciphertext; API unit tests | I19: Likelihood Very Low: the user ID never comes from the request body. Impact Moderate: content stays encrypted; records could be altered or deleted | J19: 3 | K19: 4 | L19: =J19*K19 -> 12 | M19: =INDEX(Scales!$C$12:$G$16,6-J19,K19) -> Moderate | N19: 1 | O19: 3 | P19: =N19*O19 -> 3 | Q19: =INDEX(Scales!$C$12:$G$16,6-N19,O19) -> Very Low | R19: Mitigate | S19: Add cross-user tests for the two API routes not yet covered (single-record read and delete), so every route is checked on every deploy | T19: 1 | U19: 3 | V19: =T19*U19 -> 3 | W19: =INDEX(Scales!$C$12:$G$16,6-T19,U19) -> Very Low | X19: M. Khas | Y19: Decided by M. Khas, 2026-10-31 | Z19: 2027-10-31 | AA19: Agree | AB19: I don’t want to accept this if I don’t want to, or are we saying that this isn't actually an issue?
A20: R-19 | B20: Operator locked out of administration | C20: The operator loses their phone and cannot get back into AWS or the code host because recovery has never been tested | D20: TS-06; TS-08 | F20: A-09; A-08 | G20: V-01; V-08 | H20: Account recovery options on the identity accounts; AWS root account recovery process (provided by AWS) | I20: Likelihood Low. Impact High: no fixes or account changes possible for more than a week | J20: 3 | K20: 4 | L20: =J20*K20 -> 12 | M20: =INDEX(Scales!$C$12:$G$16,6-J20,K20) -> Moderate | N20: 2 | O20: 4 | P20: =N20*O20 -> 8 | Q20: =INDEX(Scales!$C$12:$G$16,6-N20,O20) -> Low | R20: Mitigate | S20: Test recovery of administrator access from a new device; keep printed break-glass recovery codes stored offline | T20: 1 | U20: 4 | V20: =T20*U20 -> 4 | W20: =INDEX(Scales!$C$12:$G$16,6-T20,U20) -> Low | X20: M. Khas | Y20: Decided by M. Khas, 2026-10-31 | Z20: 2027-10-31 | AA20: Agree | AB20: Mitigate

Sheet Scales
A1: Likelihood (within 12 months)
A2: Value | B2: Level | C2: Definition
A3: 5 | B3: Very High | C3: Almost certain. More than once a year
A4: 4 | B4: High | C4: Likely. About once a year
A5: 3 | B5: Moderate | C5: Could happen. About once every 1-3 years
A6: 2 | B6: Low | C6: Unlikely. About once every 3-10 years
A7: 1 | B7: Very Low | C7: Highly unlikely. Less than once in 10 years
A10: Risk level matrix (SP 800-30 Table I-2). Rows = likelihood, columns = impact
B11: Likelihood \ Impact | C11: Very Low (1) | D11: Low (2) | E11: Moderate (3) | F11: High (4) | G11: Very High (5)
A12: 5 | B12: Very High (5) | C12: Very Low | D12: Low | E12: Moderate | F12: High | G12: Very High
A13: 4 | B13: High (4) | C13: Very Low | D13: Low | E13: Moderate | F13: High | G13: Very High
A14: 3 | B14: Moderate (3) | C14: Very Low | D14: Low | E14: Moderate | F14: Moderate | G14: High
A15: 2 | B15: Low (2) | C15: Very Low | D15: Low | E15: Low | F15: Low | G15: Moderate
A16: 1 | B16: Very Low (1) | C16: Very Low | D16: Very Low | E16: Very Low | F16: Low | G16: Low
A18: Impact: rate the worst effect on people, the service or the operator. Full scale in methodology.md section 3.2.

Sheet Assets
A1: ID | B1: Asset | C1: Includes | D1: C | E1: I | F1: A | G1: Why it matters
A2: A-01 | B2: User content and keyrings | C2: D-01 to D-10, D-13, stored as ciphertext in DynamoDB | D2: High | E2: High | F2: Moderate | G2: Health, mental health, religious and third-party data. Promise SC-1 depends on it
A3: A-02 | B3: Backups | C3: Point-in-time recovery (35 days), daily backup vault (35 days), copy vault in a second region (3 years) | D3: High | E3: High | F3: High | G3: The only way back from data loss. Also holds deleted users' data
A4: A-03 | B4: Record metadata | C4: D-21: record names, timestamps, sizes | D4: Moderate | E4: Low | F4: Low | G4: Readable by the administrator and AWS. Shows when users log, not what
A5: A-04 | B5: User accounts | C5: D-15 to D-20 in Cognito | D5: Moderate | E5: High | F5: Moderate | G5: Gate to each user's ciphertext and the ability to delete it
A6: A-05 | B6: Web app as delivered | C6: D-27: files in S3 served by CloudFront | D6: Low | E6: Very high | F6: Moderate | G6: Whoever controls these files controls the code that handles passphrases
A7: A-06 | B7: Source code and deploy pipeline | C7: D-26: private GitHub repository and Actions workflow | D7: Moderate | E7: Very high | F7: Low | G7: A push to main deploys to production
A8: A-07 | B8: Deploy identity | C8: GitHub OIDC deploy role and the CDK bootstrap roles it uses | D8: n/a | E8: Very high | F8: Low | G8: Can change any resource in the stack
A9: A-08 | B9: AWS account | C9: Root user, administrator IAM user, billing, account-level settings | D9: n/a | E9: Very high | F9: High | G9: Full control of everything above
A10: A-09 | B10: Administrator identities and credential store | C10: D-25: password manager and personal identity accounts used to reach AWS and GitHub (D-008) | D10: Very high | E10: Very high | F10: High | G10: The real perimeter for a one-person operation
A11: A-10 | B11: Domain, DNS and email identity | C11: Domain registration, DNS zone, TLS certificate, SES sending domain | D11: n/a | E11: Very high | F11: High | G11: Controls where users' browsers go and who can send mail as the app
A12: A-11 | B12: Sync API | C12: API Gateway and Lambda | D12: n/a | E12: High | F12: Moderate | G12: Enforces per-user access to records
... A15: A-14 | B15: Privacy commitments and request handling | C15: Commitments SC-1 to SC-5; D-24 support requests | D15: n/a | E15: n/a | F15: n/a | G15: How users' rights and expectations are met

Sheet Threat sources
A1: ID | B1: Threat source | C1: SP 800-30 type | D1: Capability | E1: Intent | F1: Targeting | G1: Notes
A2: TS-01 | B2: Opportunistic outsider (phishing kits, credential stuffing, bots) | C2: Adversarial: individual or group, outsider | D2: Moderate | E2: Money: resell accounts, mine crypto, ransom | F2: Low. Hits anyone | G2: The most common real-world source for small cloud accounts
A3: TS-02 | B3: Targeted outsider | C3: Adversarial: individual, outsider | D3: Moderate | E3: Personal: someone who knows the operator or a user | F3: Moderate | G3: Unlikely, but the users are a small, known group
A4: TS-03 | B4: Software supply-chain attacker | C4: Adversarial: group, established | D4: High | E4: Broad credential and code theft | F4: Low. Hits whoever installs the package | G4: Compromised npm packages or GitHub Actions
A5: TS-04 | B5: Trusted insider: a user, or someone close to one | C5: Adversarial: individual, trusted insider | D5: Low | E5: Curiosity, relationship conflict | F5: High. One specific person | G5: For example, a partner with access to a user's unlocked phone
A6: TS-05 | B6: Privileged insider: the operator, acting deliberately or under pressure | C6: Adversarial: individual, privileged insider | D6: Very high | E6: None today. Included because the trust model depends on it | F6: n/a | G6: See R-04
A7: TS-06 | B7: The operator's own mistakes | C7: Accidental: privileged user or administrator | D7: n/a | E7: n/a | F7: n/a | G7: Wrong command, bad deploy, misconfiguration
A8: TS-07 | B8: Software and service faults | C8: Structural: software, IT equipment | D8: n/a | E8: n/a | F8: n/a | G8: Bugs in the app or in AWS services
A9: TS-08 | B9: Infrastructure outage or disaster | C9: Environmental: infrastructure failure | D9: n/a | E9: n/a | F9: n/a | G9: AWS region outage; loss of the operator's phone or computer
A10: TS-09 | B10: Operator unavailable | C10: Added: not in Table D-2 (key person) | D10: n/a | E10: n/a | F10: n/a | G10: Illness, travel, life events
A11: TS-10 | B11: Legal and regulatory | C11: Added: not in Table D-2 | D11: n/a | E11: n/a | F11: n/a | G11: A complaint, regulator inquiry or new law. ISO 27001 clause 4.2 brings these in

Sheet Vulnerabilities
A1: ID | B1: Vulnerability | C1: Assets | D1: Source | E1: Status
A2: V-01 | B2: Administrator sign-in factors are not fully independent of each other | C2: A-08, A-09 | D2: Phase 0 interview | E2: Open
A3: V-02 | B3: A personal identity account can sign in to the code host, and the code host deploys production with no approval step | C3: A-06, A-09 | D3: Phase 0 interview; deploy.yml | E3: Open
A4: V-03 | B4: No branch protection or second reviewer on the app repository | C4: A-06 | D4: Phase 0 interview | E4: Open
A5: V-04 | B5: The deploy role can use the CDK bootstrap roles, which have broad (administrator-equivalent) permissions | C5: A-07, A-08 | D5: tracker@9124656:infra/lib/tracker-stack.ts:359-362 | E5: Open
A6: V-05 | B6: The CI pipeline doesn't pin dependencies to a lockfile, pins GitHub Actions to version tags rather than commits, and has no dependency scanning | C6: A-06, A-07 | D6: tracker@9124656:.github/workflows/deploy.yml:25-33 | E6: Open
A7: V-06 | B7: Account-level audit logging and threat detection are unverified; app logs are kept 14 days; no API or CDN access logs | C7: A-12 | D7: System description 3.1; tracker-stack.ts:190-193 | E7: Open (unverified)
A8: V-07 | B8: The backup copy vault was created by hand outside infrastructure code; backups are not locked against deletion; no restore test is on record | C8: A-02 | D8: tracker-stack.ts:306-316; DEPLOY.md Part 6 | E8: Open
A9: V-08 | B9: Recovery of administrator access after losing a device has not been tested | C9: A-09, A-08 | D9: Phase 0 interview | E9: Open
A10: V-09 | B10: Record metadata is stored unencrypted | C10: A-03 | D10: tracker@9124656:infra/lambda/api.mjs; data inventory D-21 | E10: By design
A11: V-10 | B11: Backup retention (up to 3 years) is set by a technical setting, not a retention decision, and is longer than a user would expect after deletion | C11: A-02, A-14 | D11: tracker-stack.ts:322 | E11: Open
A12: V-11 | B12: No privacy notice, terms, or log of user requests | C12: A-14 | D12: System description 2, 3.4 | E12: Open (Phase 6)
... A16: V-15 | B16: Data passphrase strength is checked by length only (12 characters) | C16: A-01 | D16: tracker@9124656:web/js/app.js:32 | E16: Open

Sheet Conditions
A1: ID | B1: Condition | C1: Effect on risk
A2: PC-01 | B2: One operator does everything | C2: No separation of duties or independent review; key-person dependency
A3: PC-02 | B3: The operator controls the code that handles users' passphrases | C3: End-to-end encryption protects stored data from the operator, but not from a changed app
A4: PC-03 | B4: Most data is special-category, and some is about people without accounts | C4: Raises the impact of any confidentiality breach
A5: PC-04 | B5: Users are friends and family | C5: Informal communication; lower likelihood of complaints; higher personal cost if trust breaks
A6: PC-05 | B6: Near-zero budget | C6: Favours free controls; paid tools need a clear risk case
A7: PC-06 | B7: The app works offline and keeps an encrypted copy on each device | C7: Lowers the impact of outages and of some data loss
A8: PC-07 | B8: All user content is end-to-end encrypted | C8: Lowers the impact of most server-side compromises to metadata and availability
